doover/__init__.py
doover/cli/__init__.py
doover/cli/cli.py
doover/cli/decorators.py
doover/cli/parsers.py
doover/cli/sub_section.py
doover/cloud/__init__.py
doover/cloud/api/__init__.py
doover/cloud/api/agent.py
doover/cloud/api/application.py
doover/cloud/api/channel.py
doover/cloud/api/client.py
doover/cloud/api/config.py
doover/cloud/api/exceptions.py
doover/cloud/api/message.py
doover/cloud/api/object.py
doover/cloud/processor/__init__.py
doover/cloud/processor/base.py
doover/config/__init__.py
doover/docker/__init__.py
doover/docker/application.py
doover/docker/grpc_generate.bash
doover/docker/grpc_interface.py
doover/docker/device_agent/__init__.py
doover/docker/device_agent/device_agent.proto
doover/docker/device_agent/device_agent.py
doover/docker/device_agent/grpc_generate.bash
doover/docker/device_agent/grpc_stubs/__init__.py
doover/docker/device_agent/grpc_stubs/device_agent_pb2.py
doover/docker/device_agent/grpc_stubs/device_agent_pb2.pyi
doover/docker/device_agent/grpc_stubs/device_agent_pb2_grpc.py
doover/docker/modbus/__init__.py
doover/docker/modbus/config.py
doover/docker/modbus/grpc_generate.bash
doover/docker/modbus/modbus_iface.proto
doover/docker/modbus/modbus_iface.py
doover/docker/modbus/grpc_stubs/__init__.py
doover/docker/modbus/grpc_stubs/modbus_iface_pb2.py
doover/docker/modbus/grpc_stubs/modbus_iface_pb2.pyi
doover/docker/modbus/grpc_stubs/modbus_iface_pb2_grpc.py
doover/docker/platform/__init__.py
doover/docker/platform/grpc_generate.bash
doover/docker/platform/platform.py
doover/docker/platform/platform_iface.proto
doover/docker/platform/platform_types.py
doover/docker/platform/grpc_stubs/__init__.py
doover/docker/platform/grpc_stubs/platform_iface_pb2.py
doover/docker/platform/grpc_stubs/platform_iface_pb2.pyi
doover/docker/platform/grpc_stubs/platform_iface_pb2_grpc.py
doover/reports/__init__.py
doover/reports/base.py
doover/reports/data.py
doover/reports/json_flatten.py
doover/reports/xlsx_base.py
doover/state/__init__.py
doover-0.4.18.dist-info/METADATA
doover-0.4.18.dist-info/WHEEL
doover-0.4.18.dist-info/entry_points.txt
doover-0.4.18.dist-info/licenses/LICENSE
doover-0.4.18.dist-info/RECORD
