Metadata-Version: 2.4
Name: doover
Version: 0.4.18
Summary: Python package for interacting with Doover
Project-URL: Homepage, https://doover.com
Author-email: Doover Team <developers@doover.com>
License-File: LICENSE
Keywords: doover,doover cli
Classifier: Development Status :: 4 - Beta
Classifier: Intended Audience :: Developers
Classifier: Natural Language :: English
Classifier: Operating System :: OS Independent
Classifier: Programming Language :: Python
Requires-Python: >=3.11
Requires-Dist: aiohttp>=3.12.13
Requires-Dist: requests==2.32.3
Provides-Extra: grpc
Requires-Dist: grpcio==1.65.1; extra == 'grpc'
Requires-Dist: protobuf==5.28.2; extra == 'grpc'
Provides-Extra: reports
Requires-Dist: pytz>=2025.2; extra == 'reports'
Requires-Dist: tzlocal>=5.3.1; extra == 'reports'
Requires-Dist: xlsxwriter>=3.2.2; extra == 'reports'
Provides-Extra: test
Requires-Dist: jsonschema>=4.23.0; extra == 'test'
Requires-Dist: pytest-asyncio>=0.26.0; extra == 'test'
Requires-Dist: pytest>=8.3.5; extra == 'test'
